[{"items":["test"],"customer":{"name":"tester","email":"test@test.com","street":"23test st","postal-code":"V3R 9V3","city":"test city"},"id":"442.69164291233733"},{"items":["test"],"customer":{"name":"tester","email":"test@test.com","street":"23test st","postal-code":"V3R 9V3","city":"test city"},"id":"129.46649838407276"},{"items":[{"id":"m3","name":"Caesar Salad","price":7.99,"quantity":5},{"id":"m2","name":"Margherita Pizza","price":12.99,"quantity":1}],"customer":{"name":"tester","email":"test@test.com","street":"23test st","postal-code":"V3R 9V3","city":"test city"},"id":"968.7172954681475"},{"items":[{"id":"m3","name":"Caesar Salad","price":7.99,"quantity":5},{"id":"m2","name":"Margherita Pizza","price":12.99,"quantity":1}],"customer":{"name":"tester","email":"test@test.com","street":"23test st","postal-code":"V3R 9V3","city":"test city"},"id":"484.5012029714022"},{"items":[{"id":"m3","name":"Caesar Salad","price":7.99,"quantity":5},{"id":"m2","name":"Margherita Pizza","price":12.99,"quantity":1}],"customer":{"name":"tester","email":"test@test.com","street":"23test st","postal-code":"V3R 9V3","city":"test city"},"id":"475.93068431032816"},{"items":[{"id":"m3","name":"Caesar Salad","price":7.99,"quantity":5},{"id":"m2","name":"Margherita Pizza","price":12.99,"quantity":1}],"customer":{"name":"tester","email":"test@test.com","street":"23test st","postal-code":"V3R 9V3","city":"test city"},"id":"345.73154029030894"},{"items":[{}],"customer":{"name":"nameanem","email":"dsfs@fsfcw.com","street":"fsdfeve","postal-code":"V3R 9V3","city":"fsdfve"},"id":"274.43265055058254"},{"items":[{}],"customer":{"name":"nameanem","email":"dsfs@fsfcw.com","street":"fsdfeve","postal-code":"V3R 9V3","city":"fsdfve"},"id":"636.8831965174242"},{"items":[{}],"customer":{"name":"tester name","email":"tester@test.com","street":"test st","postal-code":"V3R 9V3","city":"test city"},"id":"659.1923597940707"},{"items":[{}],"customer":{"name":"xvdfgvef","email":"fsdvs@FSVD.COM","street":"rsfs","postal-code":"V3R 9V3","city":"fdvedf"},"id":"560.321154413278"},{"items":[{}],"customer":{"name":"tester","email":"test@tsest.com","street":"testSt","postal-code":"V3R 9V3","city":"test city"},"id":"151.36783785783402"},{"items":[{}],"customer":{"name":"Bren Bren","email":"bren@test.com","street":"123 test st","postal-code":"V3R 9V3","city":"test city"},"id":"871.3628556523247"},{"items":[{}],"customer":{"name":"dafcadc","email":"dcas@dacsda.com","street":"efwefcw","postal-code":"V3R 9V3","city":"vsfvdf"},"id":"676.6730942393216"},{"items":[{}],"customer":{"name":"tester","email":"dsac@gvdfbd.com","street":"123st st","postal-code":"V3R 9V3","city":"sc"},"id":"974.9943668481529"},{"items":[{}],"customer":{"name":"test","email":"test@teest.com","street":"test st","postal-code":"V3R 9V3","city":"test city"},"id":"180.0006007395547"},{"items":[{"id":"m2","name":"Margherita Pizza","price":12.99,"quantity":2},{"id":"m5","name":"Veggie Burger","price":9.99,"quantity":1},{"id":"m4","name":"Spaghetti Carbonara","price":10.99,"quantity":4}],"customer":{"name":"tester","email":"test@here.com","street":"testst","postal-code":"V3R 9V3","city":"testcity"},"id":"852.5387112498364"},{"items":[{"id":"m2","name":"Margherita Pizza","price":12.99,"quantity":2}],"customer":{"name":"tester","email":"test@test.com","street":"123 testst","postal-code":"V3R 9V3","city":"test city"},"id":"108.8067218402462"},{"items":[{"id":"m2","name":"Margherita Pizza","price":12.99,"quantity":1},{"id":"m3","name":"Caesar Salad","price":7.99,"quantity":1}],"customer":{"name":"tester","email":"test@tester.com","street":"gergfer","postal-code":"V3R 9V3","city":"testcity"},"id":"799.2041173820265"},{"items":[{"id":"m3","name":"Caesar Salad","price":7.99,"quantity":2}],"customer":{"name":"sdffv","email":"ddedsc@fsdv.com","street":"fdsvc","postal-code":"V3R 9V3","city":"fsgde"},"id":"274.39434150570776"},{"items":[{"id":"m3","name":"Caesar Salad","price":7.99,"quantity":1},{"id":"m2","name":"Margherita Pizza","price":12.99,"quantity":1}],"customer":{"name":"tester","email":"asfsew@fsrg.com","street":"test","postal-code":"V3R 9V3","city":"Surrey"},"id":"620.2826595045701"},{"items":[{"id":"m2","name":"Margherita Pizza","price":12.99,"quantity":2},{"id":"m3","name":"Caesar Salad","price":7.99,"quantity":2}],"customer":{"name":"sdfds","email":"dcsd@fsrve.com","street":"123st","postal-code":"V3R 9V3","city":"Surrey"},"id":"563.0183559077988"}]